SubTest01/test1.py
SubTest01/test2.py
SubTest01-0.0.0.2.dist-info/METADATA
SubTest01-0.0.0.2.dist-info/WHEEL
SubTest01-0.0.0.2.dist-info/top_level.txt
SubTest01-0.0.0.2.dist-info/RECORD
