Metadata-Version: 2.1
Name: SubTest01
Version: 0.0.0.2
Summary: My First Test Package
Home-page: https://blog.naver.com/data_anlayze
Author: anstmdwn
Author-email: anstmdwn34@gmail.com
License: MIT
Platform: UNKNOWN
Requires-Python: >=3
